ds_modules_101/__init__.py
ds_modules_101/Data/__init__.py
ds_modules_101/Data/Docs/Word_Doc.docx
ds_modules_101/Data/HR/HR copy.csv
ds_modules_101/Data/HR/HR.csv
ds_modules_101/Data/ibd/IBD.csv
ds_modules_101/Data/titanic/titanic.csv
ds_modules_101/Models/LinearRegression.py
ds_modules_101/Models/LogisticRegression.py
ds_modules_101/Models/Microsimulation.py
ds_modules_101/Models/MultinomialLogisticRegression.py
ds_modules_101/Models/TimeSeries.py
ds_modules_101/Models/__init__.py
ds_modules_101/Models/logreg.py
ds_modules_101/Models/oaxaca.py
ds_modules_101/Models/oaxaca_old.py
ds_modules_101/Models/ordinal_logistic_regression.py
ds_modules_101/Plotting/__init__.py
ds_modules_101/Plotting/barplot.py
ds_modules_101/Plotting/cleveland_plot.py
ds_modules_101/Plotting/heatmap.py
ds_modules_101/Plotting/sankey_chart.py
ds_modules_101/Utilities/__init__.py
ds_modules_101/Utilities/word_doc_creator.py
ds_modules_101-0.9.4.dist-info/LICENSE
ds_modules_101-0.9.4.dist-info/METADATA
ds_modules_101-0.9.4.dist-info/WHEEL
ds_modules_101-0.9.4.dist-info/top_level.txt
ds_modules_101-0.9.4.dist-info/RECORD
